reqstool_python_poetry_plugin/__init__.py
reqstool_python_poetry_plugin/plugin.py
reqstool_python_poetry_plugin-0.0.4.dist-info/LICENSE
reqstool_python_poetry_plugin-0.0.4.dist-info/METADATA
reqstool_python_poetry_plugin-0.0.4.dist-info/WHEEL
reqstool_python_poetry_plugin-0.0.4.dist-info/entry_points.txt
reqstool_python_poetry_plugin-0.0.4.dist-info/RECORD
