Metadata-Version: 2.1
Name: reqstool-python-poetry-plugin
Version: 0.0.4
Summary: Reqstool Python Poetry Plugin
Home-page: https://github.com/Luftfartsverket/reqstool-python-poetry-plugin.git
License: MIT
Author: LFV SYSDEV
Author-email: sysdev@lfv.com
Requires-Python: >=3.10,<4.0
Classifier: Development Status :: 4 - Beta
Classifier: License :: OSI Approved :: MIT License
Classifier: Operating System :: OS Independent
Classifier: Programming Language :: Python :: 3
Classifier: Programming Language :: Python :: 3.10
Classifier: Programming Language :: Python :: 3.11
Classifier: Programming Language :: Python :: 3.12
Requires-Dist: poetry (==1.8.3)
Requires-Dist: poetry-dynamic-versioning (>=1.2.0,<2.0.0)
Requires-Dist: reqstool-python-decorators (==0.0.4)
Project-URL: Documentation, https://github.com/Luftfartsverket/reqstool-python-poetry-plugin.git
Project-URL: Repository, https://github.com/Luftfartsverket/reqstool-python-poetry-plugin.git
